MANIFEST.in
README.rst
setup.py
vlab_auth_service/__init__.py
vlab_auth_service/app.ini
vlab_auth_service/app.py
vlab_auth_service.egg-info/PKG-INFO
vlab_auth_service.egg-info/SOURCES.txt
vlab_auth_service.egg-info/dependency_links.txt
vlab_auth_service.egg-info/requires.txt
vlab_auth_service.egg-info/top_level.txt
vlab_auth_service/lib/__init__.py
vlab_auth_service/lib/constants.py
vlab_auth_service/lib/generate_token.py
vlab_auth_service/lib/views/__init__.py
vlab_auth_service/lib/views/healthcheck.py
vlab_auth_service/lib/views/key.py
vlab_auth_service/lib/views/token.py