Metadata-Version: 1.0
Name: vlab-auth-service
Version: 0.0.1
Summary: An authentication server for vLab
Home-page: UNKNOWN
Author: Nicholas Willhite,
Author-email: willnx84@gmail.com
License: UNKNOWN
Platform: UNKNOWN
